LICENSE
README.md
setup.cfg
setup.py
maxia_pipedrive/__init__.py
maxia_pipedrive/consts.py
maxia_pipedrive/data_handler.py
maxia_pipedrive/models.py
maxia_pipedrive/relations.py
maxia_pipedrive/tests.py
maxia_pipedrive.egg-info/PKG-INFO
maxia_pipedrive.egg-info/SOURCES.txt
maxia_pipedrive.egg-info/dependency_links.txt
maxia_pipedrive.egg-info/requires.txt
maxia_pipedrive.egg-info/top_level.txt
maxia_pipedrive/api_handler/__init__.py
maxia_pipedrive/api_handler/deals.py
maxia_pipedrive/api_handler/fields.py
maxia_pipedrive/api_handler/followers.py
maxia_pipedrive/api_handler/handler.py
maxia_pipedrive/api_handler/organizations.py
maxia_pipedrive/api_handler/persons.py
maxia_pipedrive/api_handler/products.py
maxia_pipedrive/api_handler/stages.py
maxia_pipedrive/api_handler/users.py
maxia_pipedrive/api_handler/utils.py