Metadata-Version: 2.1
Name: maxia-pipedrive
Version: 1.4
Summary: Maxia Pipedrive API handler
Home-page: https://github.com/Max-ia-Education/maxia_pipedrive_api
Author: Max.ia Education
Author-email: luiz@maxia.education
License: MIT
Download-URL: https://github.com/Max-ia-Education/maxia_pipedrive_api/archive/refs/tags/v1.3.tar.gz
Platform: UNKNOWN
Classifier: Development Status :: 3 - Alpha
Classifier: Intended Audience :: Developers
Classifier: Topic :: Software Development :: Build Tools
Classifier: License :: OSI Approved :: MIT License
Classifier: Programming Language :: Python :: 3.7
Classifier: Programming Language :: Python :: 3.8
Classifier: Programming Language :: Python :: 3.9
License-File: LICENSE
